{
    "Data": {
        "Bricks": [],
        "Objectives": [
            {
                "Id": "0cfc3712-dff1-4d78-8935-ad6c03563684",
                "Type": "statemachine",
                "Category": "primary",
                "Definition": {
                    "Scope": "Hit",
                    "States": {
                        "Start": {
                            "Kill": [
                                {
                                    "Condition": {
                                        "$eq": [
                                            "$Value.RepositoryId",
                                            "c8734bd3-d451-41a3-a4ec-eb28cb0d344e"
                                        ]
                                    },
                                    "Transition": "Success"
                                }
                            ]
                        }
                    },
                    "Context": {
                        "Targets": [
                            "c8734bd3-d451-41a3-a4ec-eb28cb0d344e"
                        ]
                    }
                },
                "HUDTemplate": {
                    "display": {
                        "$loc": {
                            "key": "UI_CONTRACT_GENERAL_OBJ_KILL",
                            "data": "$($repository c8734bd3-d451-41a3-a4ec-eb28cb0d344e).Name"
                        }
                    }
                },
                "BriefingText": {
                    "$loc": {
                        "key": "UI_CONTRACT_GENERAL_OBJ_KILL",
                        "data": "$($repository c8734bd3-d451-41a3-a4ec-eb28cb0d344e).Name"
                    }
                }
            }
        ],
        "GameChangers": []
    },
    "Metadata": {
        "Id": "4c263306-b203-44cf-acad-f3ae830b0a73",
        "Type": "usercreated",
        "Title": "Mod Order: 2024-11-04abcd",
        "Location": "LOCATION_MUMBAI",
        "PublicId": "113428830907",
        "ScenePath": "assembly:/_PRO/Scenes/Missions/Mumbai/scene_mongoose.entity",
        "TileImage": "$($repository c8734bd3-d451-41a3-a4ec-eb28cb0d344e).Image",
        "Description": "MAKE THE BRIEFING USEFUL:\r\rWhere are the required items found?\rWhat is needed to unlock them or a specific suit?\r  www.hitmaps.com\r  www.hitmanforum.com/t/2277\r\rTry to keep the contract as unrestricted as possible.\rMore general pros and cons of contract elements:\r  www.hitmanforum.com/t/2483a",
        "GameVersion": "8.17.0.65",
        "IsPublished": true,
        "Entitlements": [
            "LOCATION_MUMBAI"
        ],
        "CreatorUserId": "2cf2027f-fe60-46ba-bd3f-4c06f364f129",
        "ServerVersion": "8.17.0.65",
        "CreationTimestamp": "2024-11-05T03:16:42.5832077Z",
        "GroupObjectiveDisplayOrder": [
            {
                "Id": "0cfc3712-dff1-4d78-8935-ad6c03563684"
            }
        ]
    }
}