{
    "Data": {
        "Objectives": [
            {
                "Id": "2efe3e6a-0ed1-4275-8cc5-a7ad5a0edb25",
                "Type": "statemachine",
                "BriefingText": {
                    "$loc": {
                        "key": "UI_CONTRACT_GENERAL_OBJ_KILL",
                        "data": "$($repository ade7a3c0-132e-4329-9983-d3c4c42c7af4).Name"
                    }
                },
                "HUDTemplate": {
                    "display": {
                        "$loc": {
                            "key": "UI_CONTRACT_GENERAL_OBJ_KILL",
                            "data": "$($repository ade7a3c0-132e-4329-9983-d3c4c42c7af4).Name"
                        }
                    }
                },
                "Category": "primary",
                "Definition": {
                    "Scope": "Hit",
                    "Context": {
                        "Targets": [
                            "ade7a3c0-132e-4329-9983-d3c4c42c7af4"
                        ]
                    },
                    "States": {
                        "Start": {
                            "Kill": [
                                {
                                    "Condition": {
                                        "$eq": [
                                            "$Value.RepositoryId",
                                            "ade7a3c0-132e-4329-9983-d3c4c42c7af4"
                                        ]
                                    },
                                    "Transition": "Success"
                                }
                            ]
                        }
                    }
                },
                "TargetConditions": [
                    {
                        "Type": "hitmansuit",
                        "RepositoryId": "97e477fc-f469-4bf4-920b-c22e8f4ba800",
                        "HardCondition": false,
                        "ObjectiveId": "fafb22cb-862a-43a0-b573-3be8c825cdc5",
                        "KillMethod": ""
                    },
                    {
                        "Type": "killmethod",
                        "RepositoryId": "00000000-0000-0000-0000-000000000000",
                        "HardCondition": false,
                        "ObjectiveId": "2c58e8b3-1fa8-421f-b2e0-9d065cdc2000",
                        "KillMethod": "accident_electric"
                    }
                ]
            },
            {
                "Id": "fafb22cb-862a-43a0-b573-3be8c825cdc5",
                "Type": "statemachine",
                "Category": "secondary",
                "Definition": {
                    "Scope": "Hit",
                    "Context": {
                        "Targets": [
                            "ade7a3c0-132e-4329-9983-d3c4c42c7af4"
                        ]
                    },
                    "States": {
                        "Start": {
                            "Kill": [
                                {
                                    "Condition": {
                                        "$and": [
                                            {
                                                "$eq": [
                                                    "$Value.RepositoryId",
                                                    "ade7a3c0-132e-4329-9983-d3c4c42c7af4"
                                                ]
                                            },
                                            {
                                                "$eq": [
                                                    "$Value.OutfitIsHitmanSuit",
                                                    true
                                                ]
                                            }
                                        ]
                                    },
                                    "Transition": "Success"
                                },
                                {
                                    "Condition": {
                                        "$eq": [
                                            "$Value.RepositoryId",
                                            "ade7a3c0-132e-4329-9983-d3c4c42c7af4"
                                        ]
                                    },
                                    "Transition": "Failure"
                                }
                            ]
                        }
                    }
                }
            },
            {
                "Id": "2c58e8b3-1fa8-421f-b2e0-9d065cdc2000",
                "Type": "statemachine",
                "Category": "secondary",
                "Definition": {
                    "Scope": "Hit",
                    "Context": {
                        "Targets": [
                            "ade7a3c0-132e-4329-9983-d3c4c42c7af4"
                        ]
                    },
                    "States": {
                        "Start": {
                            "Kill": [
                                {
                                    "Condition": {
                                        "$and": [
                                            {
                                                "$eq": [
                                                    "$Value.RepositoryId",
                                                    "ade7a3c0-132e-4329-9983-d3c4c42c7af4"
                                                ]
                                            },
                                            {
                                                "$any": {
                                                    "?": {
                                                        "$eq": [
                                                            "$.#",
                                                            "accident_electric"
                                                        ]
                                                    },
                                                    "in": [
                                                        "$Value.KillMethodBroad",
                                                        "$Value.KillMethodStrict"
                                                    ]
                                                }
                                            }
                                        ]
                                    },
                                    "Transition": "Success"
                                },
                                {
                                    "Condition": {
                                        "$eq": [
                                            "$Value.RepositoryId",
                                            "ade7a3c0-132e-4329-9983-d3c4c42c7af4"
                                        ]
                                    },
                                    "Transition": "Failure"
                                }
                            ]
                        }
                    }
                }
            },
            {
                "Id": "6d45e162-6411-4fb5-8c9b-e790935dc5c7",
                "Type": "statemachine",
                "BriefingText": {
                    "$loc": {
                        "key": "UI_CONTRACT_GENERAL_OBJ_KILL",
                        "data": "$($repository a7f475df-23f6-4f4c-9907-3655d74d60c6).Name"
                    }
                },
                "HUDTemplate": {
                    "display": {
                        "$loc": {
                            "key": "UI_CONTRACT_GENERAL_OBJ_KILL",
                            "data": "$($repository a7f475df-23f6-4f4c-9907-3655d74d60c6).Name"
                        }
                    }
                },
                "Category": "primary",
                "Definition": {
                    "Scope": "Hit",
                    "Context": {
                        "Targets": [
                            "a7f475df-23f6-4f4c-9907-3655d74d60c6"
                        ]
                    },
                    "States": {
                        "Start": {
                            "Kill": [
                                {
                                    "Condition": {
                                        "$eq": [
                                            "$Value.RepositoryId",
                                            "a7f475df-23f6-4f4c-9907-3655d74d60c6"
                                        ]
                                    },
                                    "Transition": "Success"
                                }
                            ]
                        }
                    }
                },
                "TargetConditions": [
                    {
                        "Type": "hitmansuit",
                        "RepositoryId": "97e477fc-f469-4bf4-920b-c22e8f4ba800",
                        "HardCondition": false,
                        "ObjectiveId": "0a2937d8-3fb3-4d2d-820a-5e66147b7d4d",
                        "KillMethod": ""
                    },
                    {
                        "Type": "killmethod",
                        "RepositoryId": "00000000-0000-0000-0000-000000000000",
                        "HardCondition": false,
                        "ObjectiveId": "0e7cbeb9-c7df-4c6e-9803-41a6166b2222",
                        "KillMethod": "accident_electric"
                    }
                ]
            },
            {
                "Id": "0a2937d8-3fb3-4d2d-820a-5e66147b7d4d",
                "Type": "statemachine",
                "Category": "secondary",
                "Definition": {
                    "Scope": "Hit",
                    "Context": {
                        "Targets": [
                            "a7f475df-23f6-4f4c-9907-3655d74d60c6"
                        ]
                    },
                    "States": {
                        "Start": {
                            "Kill": [
                                {
                                    "Condition": {
                                        "$and": [
                                            {
                                                "$eq": [
                                                    "$Value.RepositoryId",
                                                    "a7f475df-23f6-4f4c-9907-3655d74d60c6"
                                                ]
                                            },
                                            {
                                                "$eq": [
                                                    "$Value.OutfitIsHitmanSuit",
                                                    true
                                                ]
                                            }
                                        ]
                                    },
                                    "Transition": "Success"
                                },
                                {
                                    "Condition": {
                                        "$eq": [
                                            "$Value.RepositoryId",
                                            "a7f475df-23f6-4f4c-9907-3655d74d60c6"
                                        ]
                                    },
                                    "Transition": "Failure"
                                }
                            ]
                        }
                    }
                }
            },
            {
                "Id": "0e7cbeb9-c7df-4c6e-9803-41a6166b2222",
                "Type": "statemachine",
                "Category": "secondary",
                "Definition": {
                    "Scope": "Hit",
                    "Context": {
                        "Targets": [
                            "a7f475df-23f6-4f4c-9907-3655d74d60c6"
                        ]
                    },
                    "States": {
                        "Start": {
                            "Kill": [
                                {
                                    "Condition": {
                                        "$and": [
                                            {
                                                "$eq": [
                                                    "$Value.RepositoryId",
                                                    "a7f475df-23f6-4f4c-9907-3655d74d60c6"
                                                ]
                                            },
                                            {
                                                "$any": {
                                                    "?": {
                                                        "$eq": [
                                                            "$.#",
                                                            "accident_electric"
                                                        ]
                                                    },
                                                    "in": [
                                                        "$Value.KillMethodBroad",
                                                        "$Value.KillMethodStrict"
                                                    ]
                                                }
                                            }
                                        ]
                                    },
                                    "Transition": "Success"
                                },
                                {
                                    "Condition": {
                                        "$eq": [
                                            "$Value.RepositoryId",
                                            "a7f475df-23f6-4f4c-9907-3655d74d60c6"
                                        ]
                                    },
                                    "Transition": "Failure"
                                }
                            ]
                        }
                    }
                }
            },
            {
                "Id": "14827941-e9e1-410a-9343-f8060cdb890e",
                "Type": "statemachine",
                "BriefingText": {
                    "$loc": {
                        "key": "UI_CONTRACT_GENERAL_OBJ_KILL",
                        "data": "$($repository ad71ea40-bdbe-4eb8-bad6-23eb572d4ab0).Name"
                    }
                },
                "HUDTemplate": {
                    "display": {
                        "$loc": {
                            "key": "UI_CONTRACT_GENERAL_OBJ_KILL",
                            "data": "$($repository ad71ea40-bdbe-4eb8-bad6-23eb572d4ab0).Name"
                        }
                    }
                },
                "Category": "primary",
                "Definition": {
                    "Scope": "Hit",
                    "Context": {
                        "Targets": [
                            "ad71ea40-bdbe-4eb8-bad6-23eb572d4ab0"
                        ]
                    },
                    "States": {
                        "Start": {
                            "Kill": [
                                {
                                    "Condition": {
                                        "$eq": [
                                            "$Value.RepositoryId",
                                            "ad71ea40-bdbe-4eb8-bad6-23eb572d4ab0"
                                        ]
                                    },
                                    "Transition": "Success"
                                }
                            ]
                        }
                    }
                },
                "TargetConditions": [
                    {
                        "Type": "hitmansuit",
                        "RepositoryId": "97e477fc-f469-4bf4-920b-c22e8f4ba800",
                        "HardCondition": false,
                        "ObjectiveId": "b576b93e-765b-46c1-b76c-cbe6e6ecaed0",
                        "KillMethod": ""
                    },
                    {
                        "Type": "killmethod",
                        "RepositoryId": "00000000-0000-0000-0000-000000000000",
                        "HardCondition": false,
                        "ObjectiveId": "079cd194-bf19-490c-8f16-37e9cca7a793",
                        "KillMethod": "accident_electric"
                    }
                ]
            },
            {
                "Id": "b576b93e-765b-46c1-b76c-cbe6e6ecaed0",
                "Type": "statemachine",
                "Category": "secondary",
                "Definition": {
                    "Scope": "Hit",
                    "Context": {
                        "Targets": [
                            "ad71ea40-bdbe-4eb8-bad6-23eb572d4ab0"
                        ]
                    },
                    "States": {
                        "Start": {
                            "Kill": [
                                {
                                    "Condition": {
                                        "$and": [
                                            {
                                                "$eq": [
                                                    "$Value.RepositoryId",
                                                    "ad71ea40-bdbe-4eb8-bad6-23eb572d4ab0"
                                                ]
                                            },
                                            {
                                                "$eq": [
                                                    "$Value.OutfitIsHitmanSuit",
                                                    true
                                                ]
                                            }
                                        ]
                                    },
                                    "Transition": "Success"
                                },
                                {
                                    "Condition": {
                                        "$eq": [
                                            "$Value.RepositoryId",
                                            "ad71ea40-bdbe-4eb8-bad6-23eb572d4ab0"
                                        ]
                                    },
                                    "Transition": "Failure"
                                }
                            ]
                        }
                    }
                }
            },
            {
                "Id": "079cd194-bf19-490c-8f16-37e9cca7a793",
                "Type": "statemachine",
                "Category": "secondary",
                "Definition": {
                    "Scope": "Hit",
                    "Context": {
                        "Targets": [
                            "ad71ea40-bdbe-4eb8-bad6-23eb572d4ab0"
                        ]
                    },
                    "States": {
                        "Start": {
                            "Kill": [
                                {
                                    "Condition": {
                                        "$and": [
                                            {
                                                "$eq": [
                                                    "$Value.RepositoryId",
                                                    "ad71ea40-bdbe-4eb8-bad6-23eb572d4ab0"
                                                ]
                                            },
                                            {
                                                "$any": {
                                                    "?": {
                                                        "$eq": [
                                                            "$.#",
                                                            "accident_electric"
                                                        ]
                                                    },
                                                    "in": [
                                                        "$Value.KillMethodBroad",
                                                        "$Value.KillMethodStrict"
                                                    ]
                                                }
                                            }
                                        ]
                                    },
                                    "Transition": "Success"
                                },
                                {
                                    "Condition": {
                                        "$eq": [
                                            "$Value.RepositoryId",
                                            "ad71ea40-bdbe-4eb8-bad6-23eb572d4ab0"
                                        ]
                                    },
                                    "Transition": "Failure"
                                }
                            ]
                        }
                    }
                }
            },
            {
                "Id": "7f72a409-3a5e-4f0a-97b1-7b06f3ab7d27",
                "Type": "statemachine",
                "BriefingText": {
                    "$loc": {
                        "key": "UI_CONTRACT_GENERAL_OBJ_KILL",
                        "data": "$($repository defc9d36-a84d-46b9-be2c-f3a435287e96).Name"
                    }
                },
                "HUDTemplate": {
                    "display": {
                        "$loc": {
                            "key": "UI_CONTRACT_GENERAL_OBJ_KILL",
                            "data": "$($repository defc9d36-a84d-46b9-be2c-f3a435287e96).Name"
                        }
                    }
                },
                "Category": "primary",
                "Definition": {
                    "Scope": "Hit",
                    "Context": {
                        "Targets": [
                            "defc9d36-a84d-46b9-be2c-f3a435287e96"
                        ]
                    },
                    "States": {
                        "Start": {
                            "Kill": [
                                {
                                    "Condition": {
                                        "$eq": [
                                            "$Value.RepositoryId",
                                            "defc9d36-a84d-46b9-be2c-f3a435287e96"
                                        ]
                                    },
                                    "Transition": "Success"
                                }
                            ]
                        }
                    }
                },
                "TargetConditions": [
                    {
                        "Type": "hitmansuit",
                        "RepositoryId": "97e477fc-f469-4bf4-920b-c22e8f4ba800",
                        "HardCondition": false,
                        "ObjectiveId": "5a529c97-e707-49e5-9eb0-ad6f9c03cdaa",
                        "KillMethod": ""
                    },
                    {
                        "Type": "killmethod",
                        "RepositoryId": "00000000-0000-0000-0000-000000000000",
                        "HardCondition": false,
                        "ObjectiveId": "98e98301-d11a-4375-9cfb-4328dda7dd99",
                        "KillMethod": "accident_electric"
                    }
                ]
            },
            {
                "Id": "5a529c97-e707-49e5-9eb0-ad6f9c03cdaa",
                "Type": "statemachine",
                "Category": "secondary",
                "Definition": {
                    "Scope": "Hit",
                    "Context": {
                        "Targets": [
                            "defc9d36-a84d-46b9-be2c-f3a435287e96"
                        ]
                    },
                    "States": {
                        "Start": {
                            "Kill": [
                                {
                                    "Condition": {
                                        "$and": [
                                            {
                                                "$eq": [
                                                    "$Value.RepositoryId",
                                                    "defc9d36-a84d-46b9-be2c-f3a435287e96"
                                                ]
                                            },
                                            {
                                                "$eq": [
                                                    "$Value.OutfitIsHitmanSuit",
                                                    true
                                                ]
                                            }
                                        ]
                                    },
                                    "Transition": "Success"
                                },
                                {
                                    "Condition": {
                                        "$eq": [
                                            "$Value.RepositoryId",
                                            "defc9d36-a84d-46b9-be2c-f3a435287e96"
                                        ]
                                    },
                                    "Transition": "Failure"
                                }
                            ]
                        }
                    }
                }
            },
            {
                "Id": "98e98301-d11a-4375-9cfb-4328dda7dd99",
                "Type": "statemachine",
                "Category": "secondary",
                "Definition": {
                    "Scope": "Hit",
                    "Context": {
                        "Targets": [
                            "defc9d36-a84d-46b9-be2c-f3a435287e96"
                        ]
                    },
                    "States": {
                        "Start": {
                            "Kill": [
                                {
                                    "Condition": {
                                        "$and": [
                                            {
                                                "$eq": [
                                                    "$Value.RepositoryId",
                                                    "defc9d36-a84d-46b9-be2c-f3a435287e96"
                                                ]
                                            },
                                            {
                                                "$any": {
                                                    "?": {
                                                        "$eq": [
                                                            "$.#",
                                                            "accident_electric"
                                                        ]
                                                    },
                                                    "in": [
                                                        "$Value.KillMethodBroad",
                                                        "$Value.KillMethodStrict"
                                                    ]
                                                }
                                            }
                                        ]
                                    },
                                    "Transition": "Success"
                                },
                                {
                                    "Condition": {
                                        "$eq": [
                                            "$Value.RepositoryId",
                                            "defc9d36-a84d-46b9-be2c-f3a435287e96"
                                        ]
                                    },
                                    "Transition": "Failure"
                                }
                            ]
                        }
                    }
                }
            },
            {
                "Id": "1d94ca20-2d1c-4f35-b1bd-68f84d8b2484",
                "Type": "statemachine",
                "BriefingText": {
                    "$loc": {
                        "key": "UI_CONTRACT_GENERAL_OBJ_KILL",
                        "data": "$($repository 9351c9b6-8534-4c63-866a-8fc71c55d4f6).Name"
                    }
                },
                "HUDTemplate": {
                    "display": {
                        "$loc": {
                            "key": "UI_CONTRACT_GENERAL_OBJ_KILL",
                            "data": "$($repository 9351c9b6-8534-4c63-866a-8fc71c55d4f6).Name"
                        }
                    }
                },
                "Category": "primary",
                "Definition": {
                    "Scope": "Hit",
                    "Context": {
                        "Targets": [
                            "9351c9b6-8534-4c63-866a-8fc71c55d4f6"
                        ]
                    },
                    "States": {
                        "Start": {
                            "Kill": [
                                {
                                    "Condition": {
                                        "$eq": [
                                            "$Value.RepositoryId",
                                            "9351c9b6-8534-4c63-866a-8fc71c55d4f6"
                                        ]
                                    },
                                    "Transition": "Success"
                                }
                            ]
                        }
                    }
                },
                "TargetConditions": [
                    {
                        "Type": "hitmansuit",
                        "RepositoryId": "97e477fc-f469-4bf4-920b-c22e8f4ba800",
                        "HardCondition": false,
                        "ObjectiveId": "87b29330-d0b2-46f5-8227-07aca10d876e",
                        "KillMethod": ""
                    },
                    {
                        "Type": "killmethod",
                        "RepositoryId": "00000000-0000-0000-0000-000000000000",
                        "HardCondition": false,
                        "ObjectiveId": "f1fdcea3-7723-4473-8f1c-2af3bffc3d73",
                        "KillMethod": "accident_electric"
                    }
                ]
            },
            {
                "Id": "87b29330-d0b2-46f5-8227-07aca10d876e",
                "Type": "statemachine",
                "Category": "secondary",
                "Definition": {
                    "Scope": "Hit",
                    "Context": {
                        "Targets": [
                            "9351c9b6-8534-4c63-866a-8fc71c55d4f6"
                        ]
                    },
                    "States": {
                        "Start": {
                            "Kill": [
                                {
                                    "Condition": {
                                        "$and": [
                                            {
                                                "$eq": [
                                                    "$Value.RepositoryId",
                                                    "9351c9b6-8534-4c63-866a-8fc71c55d4f6"
                                                ]
                                            },
                                            {
                                                "$eq": [
                                                    "$Value.OutfitIsHitmanSuit",
                                                    true
                                                ]
                                            }
                                        ]
                                    },
                                    "Transition": "Success"
                                },
                                {
                                    "Condition": {
                                        "$eq": [
                                            "$Value.RepositoryId",
                                            "9351c9b6-8534-4c63-866a-8fc71c55d4f6"
                                        ]
                                    },
                                    "Transition": "Failure"
                                }
                            ]
                        }
                    }
                }
            },
            {
                "Id": "f1fdcea3-7723-4473-8f1c-2af3bffc3d73",
                "Type": "statemachine",
                "Category": "secondary",
                "Definition": {
                    "Scope": "Hit",
                    "Context": {
                        "Targets": [
                            "9351c9b6-8534-4c63-866a-8fc71c55d4f6"
                        ]
                    },
                    "States": {
                        "Start": {
                            "Kill": [
                                {
                                    "Condition": {
                                        "$and": [
                                            {
                                                "$eq": [
                                                    "$Value.RepositoryId",
                                                    "9351c9b6-8534-4c63-866a-8fc71c55d4f6"
                                                ]
                                            },
                                            {
                                                "$any": {
                                                    "?": {
                                                        "$eq": [
                                                            "$.#",
                                                            "accident_electric"
                                                        ]
                                                    },
                                                    "in": [
                                                        "$Value.KillMethodBroad",
                                                        "$Value.KillMethodStrict"
                                                    ]
                                                }
                                            }
                                        ]
                                    },
                                    "Transition": "Success"
                                },
                                {
                                    "Condition": {
                                        "$eq": [
                                            "$Value.RepositoryId",
                                            "9351c9b6-8534-4c63-866a-8fc71c55d4f6"
                                        ]
                                    },
                                    "Transition": "Failure"
                                }
                            ]
                        }
                    }
                }
            }
        ],
        "GameChangers": [
            "1efef5c0-7381-4e22-ac04-ffbd0822cc96"
        ],
        "Bricks": [],
        "Stashpoints": [
            "f26550e7-bb18-4faf-90eb-2d70cdf2eda3",
            "f82ca3c6-83dd-4ad7-9aba-c2a7f69e8f23",
            "c6b00102-ea2f-45ec-91b3-493d633522f4"
        ]
    },
    "Metadata": {
        "Id": "d0ec470f-dd44-41dc-9a5c-84a6d92257a9",
        "Title": "Всё было",
        "ScenePath": "assembly:/_pro/scenes/missions/Ancestral/scene_smoothsnake.entity",
        "Location": "LOCATION_ANCESTRAL_SMOOTHSNAKE",
        "Description": "Контракт оформлен, вам дано разрешение приступать к его выполнению. Уничтожьте все основные цели, действуя как можно чище и по возможности избегая любого постороннего ущерба.",
        "CreatorUserId": "09d92167-fa37-458a-8149-1b40d04fedee",
        "GameVersion": "8.18.0.0",
        "ServerVersion": "8.18.0.67",
        "Type": "usercreated",
        "PublicId": "133483255668",
        "TileImage": "$($repository ade7a3c0-132e-4329-9983-d3c4c42c7af4).Image",
        "GroupObjectiveDisplayOrder": [
            {
                "Id": "2efe3e6a-0ed1-4275-8cc5-a7ad5a0edb25"
            },
            {
                "Id": "fafb22cb-862a-43a0-b573-3be8c825cdc5"
            },
            {
                "Id": "2c58e8b3-1fa8-421f-b2e0-9d065cdc2000"
            },
            {
                "Id": "6d45e162-6411-4fb5-8c9b-e790935dc5c7"
            },
            {
                "Id": "0a2937d8-3fb3-4d2d-820a-5e66147b7d4d"
            },
            {
                "Id": "0e7cbeb9-c7df-4c6e-9803-41a6166b2222"
            },
            {
                "Id": "14827941-e9e1-410a-9343-f8060cdb890e"
            },
            {
                "Id": "b576b93e-765b-46c1-b76c-cbe6e6ecaed0"
            },
            {
                "Id": "079cd194-bf19-490c-8f16-37e9cca7a793"
            },
            {
                "Id": "7f72a409-3a5e-4f0a-97b1-7b06f3ab7d27"
            },
            {
                "Id": "5a529c97-e707-49e5-9eb0-ad6f9c03cdaa"
            },
            {
                "Id": "98e98301-d11a-4375-9cfb-4328dda7dd99"
            },
            {
                "Id": "1d94ca20-2d1c-4f35-b1bd-68f84d8b2484"
            },
            {
                "Id": "87b29330-d0b2-46f5-8227-07aca10d876e"
            },
            {
                "Id": "f1fdcea3-7723-4473-8f1c-2af3bffc3d73"
            }
        ],
        "IsPublished": true,
        "CreationTimestamp": "2024-12-16T20:44:03.4395265Z",
        "Entitlements": [
            "LOCATION_ANCESTRAL"
        ]
    }
}